anjana/__init__.py
anjana/anonymity/__init__.py
anjana/anonymity/_beta_likeness.py
anjana/anonymity/_delta_disclosure.py
anjana/anonymity/_k_anonymity.py
anjana/anonymity/_l_diversity.py
anjana/anonymity/_t_closeness.py
anjana/anonymity/utils/__init__.py
anjana/anonymity/utils/utils.py
anjana-1.1.0.dist-info/LICENSE
anjana-1.1.0.dist-info/METADATA
anjana-1.1.0.dist-info/WHEEL
anjana-1.1.0.dist-info/RECORD
