Metadata-Version: 2.3
Name: anjana
Version: 1.1.0
Summary: ANJANA is an open source framework for applying different anonymity techniques.
License: Apache-2.0
Keywords: anonymity,privacy
Author: Judith Sáinz-Pardo Díaz
Author-email: sainzpardo@ifca.unican.es
Maintainer: Judith Sáinz-Pardo Díaz
Maintainer-email: sainzpardo@ifca.unican.es
Requires-Python: >=3.9,<4.0
Classifier: Development Status :: 5 - Production/Stable
Classifier: Intended Audience :: Developers
Classifier: Intended Audience :: Education
Classifier: Intended Audience :: Science/Research
Classifier: License :: OSI Approved :: Apache Software License
Classifier: Programming Language :: Python :: 3
Classifier: Programming Language :: Python :: 3.9
Classifier: Programming Language :: Python :: 3.10
Classifier: Programming Language :: Python :: 3.11
Classifier: Programming Language :: Python :: 3.12
Classifier: Programming Language :: Python :: 3.13
Classifier: Programming Language :: Python :: 3 :: Only
Classifier: Topic :: Scientific/Engineering
Classifier: Topic :: Scientific/Engineering :: Mathematics
Classifier: Topic :: Security
Requires-Dist: beartype (==0.19.0)
Requires-Dist: docutils (==0.21.2)
Requires-Dist: numpy (==2.0.2)
Requires-Dist: pandas (==2.2.2)
Requires-Dist: pycanon (==1.0.3)
Requires-Dist: typing_extensions (==4.12.2)
Project-URL: Repository, https://gitlab.ifca.es/privacy-security/anjana
